livingthings/__init__.py
livingthings/animals.py
livingthings/crops.py
livingthings/main.py
livingthings/data/Animals.csv
livingthings/data/Crops.csv
recipes/__init__.py
recipes/ingredient_search.py
recipes/main.py
recipes/recipe_search.py
recipes/data/wiki.xlsx
Stardew_Valley_Wiki-2.0.7.dist-info/METADATA
Stardew_Valley_Wiki-2.0.7.dist-info/WHEEL
Stardew_Valley_Wiki-2.0.7.dist-info/top_level.txt
Stardew_Valley_Wiki-2.0.7.dist-info/RECORD
