Metadata-Version: 2.1
Name: Stardew-Valley-Wiki
Version: 2.0.7
Summary: An example package
Author-email: Skylar Shao <shaoskylar@gmail.com>, Yuzhu Han <anlilas031326@gmail.com>
Project-URL: Homepage, https://github.com/SkylarShao97/Stardew-Valley_Wiki
Project-URL: Issues, https://github.com/SkylarShao97/Stardew-Valley_Wiki/issues
Classifier: Programming Language :: Python :: 3
Classifier: License :: OSI Approved :: MIT License
Classifier: Operating System :: OS Independent
Requires-Python: >=3.8
